Metadata-Version: 2.1
Name: sufiyakacalci
Version: 0.0.1
Summary: this is a trial package used for calculation.
Home-page: UNKNOWN
Author: Sufiya naaz
Author-email: suufiiya@gmail.com
License: MIT
Platform: UNKNOWN
License-File: LICENCE.txt
